MANIFEST.in
NEWS.rst
README.rst
setup.py
src/setuptools_pep8/__init__.py
src/setuptools_pep8/setuptools_command.py
src/setuptools_pep8.egg-info/PKG-INFO
src/setuptools_pep8.egg-info/SOURCES.txt
src/setuptools_pep8.egg-info/dependency_links.txt
src/setuptools_pep8.egg-info/entry_points.txt
src/setuptools_pep8.egg-info/not-zip-safe
src/setuptools_pep8.egg-info/requires.txt
src/setuptools_pep8.egg-info/top_level.txt
src/tests/__init__.py
src/tests/test_pep8_command.py