Metadata-Version: 1.1
Name: setuptools-pep8
Version: 0.2.0
Summary: pep8 command for setuptools
Home-page: https://github.com/CraigJPerry/setuptools-pep8
Author: Craig J Perry
Author-email: craigp84@gmail.com
License: BSD
Keywords: pep8 setuptools command
Platform: UNKNOWN
Classifier: Topic :: Documentation
Classifier: Framework :: Setuptools Plugin
Classifier: Development Status :: 5 - Production/Stable
Classifier: Programming Language :: Python
Classifier: Intended Audience :: Developers
Classifier: Operating System :: OS Independent
Classifier: License :: OSI Approved :: BSD License
Classifier: Topic :: Software Development :: Documentation
Classifier: Topic :: Software Development :: Libraries :: Python Modules
